skytemple_rust.pypy310-pp73-darwin.so
skytemple_rust-1.8.5.dist-info/RECORD
skytemple_rust-1.8.5.dist-info/LICENSE
skytemple_rust-1.8.5.dist-info/WHEEL
skytemple_rust-1.8.5.dist-info/top_level.txt
skytemple_rust-1.8.5.dist-info/METADATA
skytemple_rust/st_dpc.pyi
skytemple_rust/st_bpc.pyi
skytemple_rust/st_bpa.pyi
skytemple_rust/__init__.pyi
skytemple_rust/pmd_wan.pyi
skytemple_rust/st_sir0.pyi
skytemple_rust/st_dbg.pyi
skytemple_rust/st_pkdpx.pyi
skytemple_rust/st_md.pyi
skytemple_rust/st_waza_p.pyi
skytemple_rust/st_string.pyi
skytemple_rust/st_item_p.pyi
skytemple_rust/st_atupx.pyi
skytemple_rust/st_bg_list_dat.pyi
skytemple_rust/st_mappa_bin.pyi
skytemple_rust/st_dma.pyi
skytemple_rust/st_dpci.pyi
skytemple_rust/st_at3px.pyi
skytemple_rust/st_bma.pyi
skytemple_rust/st_dpla.pyi
skytemple_rust/py.typed
skytemple_rust/st_bpl.pyi
skytemple_rust/st_bgp.pyi
skytemple_rust/st_kao.pyi
skytemple_rust/st_at4pn.pyi
skytemple_rust/st_script_var_table.pyi
skytemple_rust/st_dpl.pyi
skytemple_rust/st_at4px.pyi
