Metadata-Version: 2.1
Name: skytemple-rust
Version: 1.8.5
Summary: Binary Rust extension for skytemple-files
Author-email: "Marco \"Capypara\" Köpcke" <hello@capypara.de>
License: GPL-3.0-or-later
Project-URL: Homepage, https://skytemple.org
Project-URL: Announcements, https://blog.skytemple.org
Project-URL: Documentation, https://wiki.skytemple.org
Project-URL: Repository, https://github.com/SkyTemple/skytemple-rust.git
Project-URL: Issues, https://github.com/SkyTemple/skytemple-rust/issues
Project-URL: Discord, https://discord.gg/skytemple
Keywords: rom-hacking,game-modding,skytemple,gtk
Classifier: Development Status :: 4 - Beta
Classifier: Programming Language :: Python
Classifier: License :: OSI Approved :: GNU General Public License v3 or later (GPLv3+)
Classifier: Programming Language :: Python :: 3.10
Classifier: Programming Language :: Python :: 3.11
Classifier: Programming Language :: Python :: 3.12
Classifier: Programming Language :: Python :: 3.13
Requires-Python: >=3.10
License-File: LICENSE
Requires-Dist: range-typed-integers>=1.0.0
